LICENCE
README.md
setup.cfg
setup.py
test/test.py
timezonedb/__init__.py
timezonedb/config.py
timezonedb/timezonedbapi.py
timezonedb.egg-info/PKG-INFO
timezonedb.egg-info/SOURCES.txt
timezonedb.egg-info/dependency_links.txt
timezonedb.egg-info/requires.txt
timezonedb.egg-info/top_level.txt