Metadata-Version: 2.1
Name: timezonedb
Version: 0.1
Summary: timezonedb.com API [python wrapper]
Home-page: https://github.com/abrihter/timezonedb/releases
Author: bojan
Author-email: 
License: MIT
Download-URL: https://github.com/abrihter/timezonedb/archive/refs/tags/v_01.tar.gz
Keywords: TIMEZONEDB,API,WRAPPER
Platform: UNKNOWN
Classifier: Development Status :: 5 - Production/Stable
Classifier: Intended Audience :: Developers
Classifier: Topic :: Software Development :: Build Tools
Classifier: License :: OSI Approved :: MIT License
Classifier: Programming Language :: Python :: 3
